{
  "version": "5.1.1",
  "flags": {},
  "shapes": [
    {
      "label": "corners",
      "points": [
        [
          14.579831932773082,
          228.57142857142858
        ],
        [
          56.00840336134448,
          299.0
        ],
        [
          465.0,
          299.0
        ],
        [
          464.5798319327731,
          109.2436974789916
        ],
        [
          289.78991596638656,
          23.949579831932773
        ],
        [
          14.999999999999972,
          91.1764705882353
        ]
      ],
      "group_id": null,
      "shape_type": "polygon",
      "flags": {}
    }
  ],
  "imagePath": "269360a475423d65a93dbfacb3d20b4cf505cc57.jpeg",
  "imageData": null,
  "imageHeight": 300,
  "imageWidth": 480
}