{
  "version": "5.1.1",
  "flags": {},
  "shapes": [
    {
      "label": "corners",
      "points": [
        [
          165.42016806722688,
          78.15126050420167
        ],
        [
          349.03361344537814,
          57.56302521008404
        ],
        [
          390.21008403361344,
          239.07563025210086
        ],
        [
          173.4033613445378,
          261.3445378151261
        ]
      ],
      "group_id": null,
      "shape_type": "polygon",
      "flags": {}
    }
  ],
  "imagePath": "dscf2121.mov-1500.jpeg",
  "imageData": null,
  "imageHeight": 300,
  "imageWidth": 480
}