{
  "version": "5.1.1",
  "flags": {},
  "shapes": [
    {
      "label": "corners",
      "points": [
        [
          299.8739495798319,
          153.78151260504202
        ],
        [
          215.42016806722688,
          195.7983193277311
        ],
        [
          162.89915966386553,
          137.39495798319328
        ],
        [
          243.15126050420167,
          107.98319327731093
        ]
      ],
      "group_id": null,
      "shape_type": "polygon",
      "flags": {}
    }
  ],
  "imagePath": "IMG_2600.jpeg",
  "imageData": null,
  "imageHeight": 300,
  "imageWidth": 480
}