{
  "version": "5.1.1",
  "flags": {},
  "shapes": [
    {
      "label": "corners",
      "points": [
        [
          213.73949579831933,
          293.69747899159665
        ],
        [
          134.32773109243695,
          251.68067226890756
        ],
        [
          40.21008403361342,
          197.47899159663865
        ],
        [
          39.78991596638652,
          150.8403361344538
        ],
        [
          181.80672268907563,
          75.21008403361344
        ],
        [
          203.65546218487393,
          65.12605042016807
        ],
        [
          302.39495798319325,
          89.07563025210084
        ],
        [
          440.21008403361344,
          121.00840336134453
        ],
        [
          356.9945047681994,
          299.0
        ],
        [
          228.0252100840336,
          299.0
        ]
      ],
      "group_id": null,
      "shape_type": "polygon",
      "flags": {}
    }
  ],
  "imagePath": "5cbe27d36391652db87e51c4806f8aa4596effe1.jpeg",
  "imageData": null,
  "imageHeight": 300,
  "imageWidth": 480
}